ckanext_downloadall-0.1.0-py2.7-nspkg.pth
ckanext/downloadall/__init__.py
ckanext/downloadall/action.py
ckanext/downloadall/cli.py
ckanext/downloadall/helpers.py
ckanext/downloadall/plugin.py
ckanext/downloadall/tasks.py
ckanext/downloadall/templates/package/read.html
ckanext/downloadall/templates/package/snippets/resources.html
ckanext/downloadall/templates/snippets/package_item.html
ckanext/downloadall/tests/__init__.py
ckanext/downloadall/tests/test_action.py
ckanext/downloadall/tests/test_plugin.py
ckanext/downloadall/tests/test_tasks.py
ckanext_downloadall-0.1.0.dist-info/LICENSE
ckanext_downloadall-0.1.0.dist-info/METADATA
ckanext_downloadall-0.1.0.dist-info/WHEEL
ckanext_downloadall-0.1.0.dist-info/entry_points.txt
ckanext_downloadall-0.1.0.dist-info/namespace_packages.txt
ckanext_downloadall-0.1.0.dist-info/top_level.txt
ckanext_downloadall-0.1.0.dist-info/RECORD
