Metadata-Version: 2.1
Name: ckanext-downloadall
Version: 0.1.0
Summary: CKAN extension that adds a "Download all" button to a dataset
Home-page: https://github.com/davidread/ckanext-downloadall
Author: David Read, Ian Ward
Author-email: david.read@hackneyworkshop.com
License: AGPL
Keywords: CKAN download
Platform: UNKNOWN
Classifier: Development Status :: 4 - Beta
Classifier: License :: OSI Approved :: GNU Affero General Public License v3 or later (AGPLv3+)
Classifier: Programming Language :: Python :: 2.7
Requires-Dist: ckanapi (>=4.3)
